Metadata-Version: 2.1
Name: Secret-helper
Version: 0.0.6
Summary: A helper function to get the secrets
Home-page: UNKNOWN
Author: Pranav Chandran
Author-email: pranav.chandran@gmail.com
License: MIT
Keywords: Secret_helper
Platform: UNKNOWN
Classifier: Development Status :: 5 - Production/Stable
Classifier: Intended Audience :: Developers
Classifier: License :: OSI Approved :: MIT License
Classifier: Operating System :: OS Independent
Classifier: Programming Language :: Python :: 3
License-File: LICENSE.txt
